chiarpc/__init__.py
chiarpc/client.py
chiarpc/farmer.py
chiarpc/harvester.py
chiarpc-0.0.2.dist-info/METADATA
chiarpc-0.0.2.dist-info/WHEEL
chiarpc-0.0.2.dist-info/top_level.txt
chiarpc-0.0.2.dist-info/RECORD
